optim_query
