Metadata-Version: 2.1
Name: optim-query
Version: 0.0.9
Summary: Fine-tune BERT for vectorized query search
Home-page: https://github.com/afurkank/optim_query
Author: Ahmet Furkan Karacık
Author-email: furkan.karacikq@gmail.com
License: MIT
License-File: LICENSE
